nautobot_broker_nats/__init__.py
nautobot_broker_nats/broker.py
nautobot_broker_nats/client.py
nautobot_broker_nats/log.py
nautobot_broker_nats-1.1.0.dist-info/METADATA
nautobot_broker_nats-1.1.0.dist-info/WHEEL
nautobot_broker_nats-1.1.0.dist-info/licenses/LICENSE
nautobot_broker_nats-1.1.0.dist-info/RECORD
